[
    {
        "id": "1",
        "competitionId": "4",
        "teamId": "NIB",
        "season": "2012",
        "ranking": "1",
        "rankingStatus": "WINNER",
        "played": "0",
        "points": "0",
        "won": "0",
        "drawn": "0",
        "lost": "0",
        "goals": "0",
        "goalsAgainst": "0",
        "goalsDifference": "0",
        "yellowCards": "0",
        "redCards": "0",
        "note": ""
    },
    {
        "id": "2",
        "competitionId": "4",
        "teamId": "DAN",
        "season": "2012",
        "ranking": "2",
        "rankingStatus": "RUNNER_UP",
        "played": "0",
        "points": "0",
        "won": "0",
        "drawn": "0",
        "lost": "0",
        "goals": "0",
        "goalsAgainst": "0",
        "goalsDifference": "0",
        "yellowCards": "0",
        "redCards": "0",
        "note": ""
    },
    {
        "id": "3",
        "competitionId": "4",
        "teamId": "LAN",
        "season": "2012",
        "ranking": "3",
        "rankingStatus": "",
        "played": "0",
        "points": "0",
        "won": "0",
        "drawn": "0",
        "lost": "0",
        "goals": "0",
        "goalsAgainst": "0",
        "goalsDifference": "0",
        "yellowCards": "0",
        "redCards": "0",
        "note": ""
    },
    {
        "id": "4",
        "competitionId": "4",
        "teamId": "DON",
        "season": "2012",
        "ranking": "4",
        "rankingStatus": "",
        "played": "0",
        "points": "0",
        "won": "0",
        "drawn": "0",
        "lost": "0",
        "goals": "0",
        "goalsAgainst": "0",
        "goalsDifference": "0",
        "yellowCards": "0",
        "redCards": "0",
        "note": ""
    },
    {
        "id": "5",
        "competitionId": "4",
        "teamId": "NIB",
        "season": "2013",
        "ranking": "1",
        "rankingStatus": "WINNER",
        "played": "0",
        "points": "0",
        "won": "0",
        "drawn": "0",
        "lost": "0",
        "goals": "0",
        "goalsAgainst": "0",
        "goalsDifference": "0",
        "yellowCards": "0",
        "redCards": "0",
        "note": ""
    },
    {
        "id": "6",
        "competitionId": "4",
        "teamId": "DAN",
        "season": "2013",
        "ranking": "2",
        "rankingStatus": "RUNNER_UP",
        "played": "0",
        "points": "0",
        "won": "0",
        "drawn": "0",
        "lost": "0",
        "goals": "0",
        "goalsAgainst": "0",
        "goalsDifference": "0",
        "yellowCards": "0",
        "redCards": "0",
        "note": ""
    },
    {
        "id": "7",
        "competitionId": "4",
        "teamId": "LAN",
        "season": "2013",
        "ranking": "3",
        "rankingStatus": "",
        "played": "0",
        "points": "0",
        "won": "0",
        "drawn": "0",
        "lost": "0",
        "goals": "0",
        "goalsAgainst": "0",
        "goalsDifference": "0",
        "yellowCards": "0",
        "redCards": "0",
        "note": ""
    },
    {
        "id": "8",
        "competitionId": "4",
        "teamId": "DON",
        "season": "2013",
        "ranking": "4",
        "rankingStatus": "",
        "played": "0",
        "points": "0",
        "won": "0",
        "drawn": "0",
        "lost": "0",
        "goals": "0",
        "goalsAgainst": "0",
        "goalsDifference": "0",
        "yellowCards": "0",
        "redCards": "0",
        "note": ""
    },
    {
        "id": "9",
        "competitionId": "4",
        "teamId": "HAP",
        "season": "2014",
        "ranking": "1",
        "rankingStatus": "WINNER",
        "played": "0",
        "points": "0",
        "won": "0",
        "drawn": "0",
        "lost": "0",
        "goals": "0",
        "goalsAgainst": "0",
        "goalsDifference": "0",
        "yellowCards": "0",
        "redCards": "0",
        "note": ""
    },
    {
        "id": "10",
        "competitionId": "4",
        "teamId": "BIDU",
        "season": "2014",
        "ranking": "2",
        "rankingStatus": "RUNNER_UP",
        "played": "0",
        "points": "0",
        "won": "0",
        "drawn": "0",
        "lost": "0",
        "goals": "0",
        "goalsAgainst": "0",
        "goalsDifference": "0",
        "yellowCards": "0",
        "redCards": "0",
        "note": ""
    },
    {
        "id": "11",
        "competitionId": "4",
        "teamId": "LAN",
        "season": "2014",
        "ranking": "3",
        "rankingStatus": "",
        "played": "0",
        "points": "0",
        "won": "0",
        "drawn": "0",
        "lost": "0",
        "goals": "0",
        "goalsAgainst": "0",
        "goalsDifference": "0",
        "yellowCards": "0",
        "redCards": "0",
        "note": ""
    },
    {
        "id": "12",
        "competitionId": "4",
        "teamId": "GLA",
        "season": "2014",
        "ranking": "4",
        "rankingStatus": "",
        "played": "0",
        "points": "0",
        "won": "0",
        "drawn": "0",
        "lost": "0",
        "goals": "0",
        "goalsAgainst": "0",
        "goalsDifference": "0",
        "yellowCards": "0",
        "redCards": "0",
        "note": ""
    },
    {
        "id": "13",
        "competitionId": "4",
        "teamId": "BIDU",
        "season": "2015",
        "ranking": "1",
        "rankingStatus": "WINNER",
        "played": "0",
        "points": "0",
        "won": "0",
        "drawn": "0",
        "lost": "0",
        "goals": "0",
        "goalsAgainst": "0",
        "goalsDifference": "0",
        "yellowCards": "0",
        "redCards": "0",
        "note": ""
    },
    {
        "id": "14",
        "competitionId": "4",
        "teamId": "HAN",
        "season": "2015",
        "ranking": "2",
        "rankingStatus": "RUNNER_UP",
        "played": "0",
        "points": "0",
        "won": "0",
        "drawn": "0",
        "lost": "0",
        "goals": "0",
        "goalsAgainst": "0",
        "goalsDifference": "0",
        "yellowCards": "0",
        "redCards": "0",
        "note": ""
    },
    {
        "id": "15",
        "competitionId": "4",
        "teamId": "LAN",
        "season": "2015",
        "ranking": "3",
        "rankingStatus": "",
        "played": "0",
        "points": "0",
        "won": "0",
        "drawn": "0",
        "lost": "0",
        "goals": "0",
        "goalsAgainst": "0",
        "goalsDifference": "0",
        "yellowCards": "0",
        "redCards": "0",
        "note": ""
    },
    {
        "id": "16",
        "competitionId": "4",
        "teamId": "HAP",
        "season": "2015",
        "ranking": "4",
        "rankingStatus": "",
        "played": "0",
        "points": "0",
        "won": "0",
        "drawn": "0",
        "lost": "0",
        "goals": "0",
        "goalsAgainst": "0",
        "goalsDifference": "0",
        "yellowCards": "0",
        "redCards": "0",
        "note": ""
    },
    {
        "id": "17",
        "competitionId": "4",
        "teamId": "QNI",
        "season": "2016",
        "ranking": "1",
        "rankingStatus": "WINNER",
        "played": "0",
        "points": "0",
        "won": "0",
        "drawn": "0",
        "lost": "0",
        "goals": "0",
        "goalsAgainst": "0",
        "goalsDifference": "0",
        "yellowCards": "0",
        "redCards": "0",
        "note": ""
    },
    {
        "id": "18",
        "competitionId": "4",
        "teamId": "HAN",
        "season": "2016",
        "ranking": "2",
        "rankingStatus": "RUNNER_UP",
        "played": "0",
        "points": "0",
        "won": "0",
        "drawn": "0",
        "lost": "0",
        "goals": "0",
        "goalsAgainst": "0",
        "goalsDifference": "0",
        "yellowCards": "0",
        "redCards": "0",
        "note": ""
    },
    {
        "id": "19",
        "competitionId": "4",
        "teamId": "BIDU",
        "season": "2016",
        "ranking": "3",
        "rankingStatus": "",
        "played": "0",
        "points": "0",
        "won": "0",
        "drawn": "0",
        "lost": "0",
        "goals": "0",
        "goalsAgainst": "0",
        "goalsDifference": "0",
        "yellowCards": "0",
        "redCards": "0",
        "note": ""
    },
    {
        "id": "20",
        "competitionId": "4",
        "teamId": "QNA",
        "season": "2016",
        "ranking": "4",
        "rankingStatus": "",
        "played": "0",
        "points": "0",
        "won": "0",
        "drawn": "0",
        "lost": "0",
        "goals": "0",
        "goalsAgainst": "0",
        "goalsDifference": "0",
        "yellowCards": "0",
        "redCards": "0",
        "note": ""
    },
    {
        "id": "21",
        "competitionId": "4",
        "teamId": "NAN",
        "season": "2017",
        "ranking": "1",
        "rankingStatus": "WINNER",
        "played": "0",
        "points": "0",
        "won": "0",
        "drawn": "0",
        "lost": "0",
        "goals": "0",
        "goalsAgainst": "0",
        "goalsDifference": "0",
        "yellowCards": "0",
        "redCards": "0",
        "note": ""
    },
    {
        "id": "22",
        "competitionId": "4",
        "teamId": "BIDU",
        "season": "2017",
        "ranking": "2",
        "rankingStatus": "RUNNER_UP",
        "played": "0",
        "points": "0",
        "won": "0",
        "drawn": "0",
        "lost": "0",
        "goals": "0",
        "goalsAgainst": "0",
        "goalsDifference": "0",
        "yellowCards": "0",
        "redCards": "0",
        "note": ""
    },
    {
        "id": "23",
        "competitionId": "4",
        "teamId": "QNA",
        "season": "2017",
        "ranking": "3",
        "rankingStatus": "",
        "played": "0",
        "points": "0",
        "won": "0",
        "drawn": "0",
        "lost": "0",
        "goals": "0",
        "goalsAgainst": "0",
        "goalsDifference": "0",
        "yellowCards": "0",
        "redCards": "0",
        "note": ""
    },
    {
        "id": "24",
        "competitionId": "4",
        "teamId": "DAN",
        "season": "2017",
        "ranking": "4",
        "rankingStatus": "",
        "played": "0",
        "points": "0",
        "won": "0",
        "drawn": "0",
        "lost": "0",
        "goals": "0",
        "goalsAgainst": "0",
        "goalsDifference": "0",
        "yellowCards": "0",
        "redCards": "0",
        "note": ""
    },
    {
        "id": "25",
        "competitionId": "4",
        "teamId": "BIDU",
        "season": "2018",
        "ranking": "1",
        "rankingStatus": "WINNER",
        "played": "0",
        "points": "0",
        "won": "0",
        "drawn": "0",
        "lost": "0",
        "goals": "0",
        "goalsAgainst": "0",
        "goalsDifference": "0",
        "yellowCards": "0",
        "redCards": "0",
        "note": ""
    },
    {
        "id": "26",
        "competitionId": "4",
        "teamId": "THH",
        "season": "2018",
        "ranking": "2",
        "rankingStatus": "RUNNER_UP",
        "played": "0",
        "points": "0",
        "won": "0",
        "drawn": "0",
        "lost": "0",
        "goals": "0",
        "goalsAgainst": "0",
        "goalsDifference": "0",
        "yellowCards": "0",
        "redCards": "0",
        "note": ""
    },
    {
        "id": "27",
        "competitionId": "4",
        "teamId": "HAN",
        "season": "2018",
        "ranking": "3",
        "rankingStatus": "",
        "played": "0",
        "points": "0",
        "won": "0",
        "drawn": "0",
        "lost": "0",
        "goals": "0",
        "goalsAgainst": "0",
        "goalsDifference": "0",
        "yellowCards": "0",
        "redCards": "0",
        "note": ""
    },
    {
        "id": "28",
        "competitionId": "4",
        "teamId": "NAN",
        "season": "2018",
        "ranking": "4",
        "rankingStatus": "",
        "played": "0",
        "points": "0",
        "won": "0",
        "drawn": "0",
        "lost": "0",
        "goals": "0",
        "goalsAgainst": "0",
        "goalsDifference": "0",
        "yellowCards": "0",
        "redCards": "0",
        "note": ""
    },
    {
        "id": "29",
        "competitionId": "4",
        "teamId": "HAN",
        "season": "2019",
        "ranking": "1",
        "rankingStatus": "WINNER",
        "played": "0",
        "points": "0",
        "won": "0",
        "drawn": "0",
        "lost": "0",
        "goals": "0",
        "goalsAgainst": "0",
        "goalsDifference": "0",
        "yellowCards": "0",
        "redCards": "0",
        "note": ""
    },
    {
        "id": "30",
        "competitionId": "4",
        "teamId": "QNA",
        "season": "2019",
        "ranking": "2",
        "rankingStatus": "RUNNER_UP",
        "played": "0",
        "points": "0",
        "won": "0",
        "drawn": "0",
        "lost": "0",
        "goals": "0",
        "goalsAgainst": "0",
        "goalsDifference": "0",
        "yellowCards": "0",
        "redCards": "0",
        "note": ""
    },
    {
        "id": "31",
        "competitionId": "4",
        "teamId": "HCM",
        "season": "2019",
        "ranking": "3",
        "rankingStatus": "",
        "played": "0",
        "points": "0",
        "won": "0",
        "drawn": "0",
        "lost": "0",
        "goals": "0",
        "goalsAgainst": "0",
        "goalsDifference": "0",
        "yellowCards": "0",
        "redCards": "0",
        "note": ""
    },
    {
        "id": "32",
        "competitionId": "4",
        "teamId": "BIDU",
        "season": "2019",
        "ranking": "4",
        "rankingStatus": "",
        "played": "0",
        "points": "0",
        "won": "0",
        "drawn": "0",
        "lost": "0",
        "goals": "0",
        "goalsAgainst": "0",
        "goalsDifference": "0",
        "yellowCards": "0",
        "redCards": "0",
        "note": ""
    }
]