[
    {
        "id": "TIER_CUP-2013-1/16-DOT-QNA",
        "competitionId": "National Cup",
        "competitionTier": "TIER_CUP",
        "season": "2013",
        "round": "1/16",
        "status": "FINISHED",
        "date": "2013-03-16",
        "time": "15:30",
        "stadium": "\u0110\u1ed3ng Th\u00e1p",
        "homeId": "DOT",
        "homeTeam": "\u0110\u1ed3ng Th\u00e1p",
        "homeScore": "0",
        "awayScore": "0",
        "awayId": "QNA",
        "awayTeam": "Qu\u1ea3ng Nam",
        "note": "Qu\u1ea3ng Nam"
    },
    {
        "id": "TIER_CUP-2013-1/16-ANGI-CAT",
        "competitionId": "National Cup",
        "competitionTier": "TIER_CUP",
        "season": "2013",
        "round": "1/16",
        "status": "FINISHED",
        "date": "2013-03-16",
        "time": "15:30",
        "stadium": "Ki\u00ean Giang",
        "homeId": "ANGI",
        "homeTeam": "An Giang",
        "homeScore": "4",
        "awayScore": "0",
        "awayId": "CAT",
        "awayTeam": "C\u1ea7n Th\u01a1",
        "note": "An Giang"
    },
    {
        "id": "TIER_CUP-2013-1/8-QNA-HAP",
        "competitionId": "National Cup",
        "competitionTier": "TIER_CUP",
        "season": "2013",
        "round": "1/8",
        "status": "FINISHED",
        "date": "2013-03-24",
        "time": "15:30",
        "stadium": "Qu\u1ea3ng Nam",
        "homeId": "QNA",
        "homeTeam": "Qu\u1ea3ng Nam",
        "homeScore": "1",
        "awayScore": "0",
        "awayId": "HAP",
        "awayTeam": "H\u1ea3i Ph\u00f2ng",
        "note": "Qu\u1ea3ng Nam"
    },
    {
        "id": "TIER_CUP-2013-1/8-HAN-KLKG",
        "competitionId": "National Cup",
        "competitionTier": "TIER_CUP",
        "season": "2013",
        "round": "1/8",
        "status": "FINISHED",
        "date": "2013-03-25",
        "time": "16:00",
        "stadium": "H\u00e0ng \u0110\u1eaby",
        "homeId": "HAN",
        "homeTeam": "H\u00e0 N\u1ed9i",
        "homeScore": "3",
        "awayScore": "3",
        "awayId": "KLKG",
        "awayTeam": "Kienlongbank Ki\u00ean Giang",
        "note": "H\u00e0 N\u1ed9i"
    },
    {
        "id": "TIER_CUP-2013-1/8-GLA-XTSG",
        "competitionId": "National Cup",
        "competitionTier": "TIER_CUP",
        "season": "2013",
        "round": "1/8",
        "status": "FINISHED",
        "date": "2013-03-25",
        "time": "16:00",
        "stadium": "Pleiku",
        "homeId": "GLA",
        "homeTeam": "Ho\u00e0ng Anh Gia Lai",
        "homeScore": "2",
        "awayScore": "1",
        "awayId": "XTSG",
        "awayTeam": "Xu\u00e2n Th\u00e0nh S\u00e0i G\u00f2n",
        "note": "Ho\u00e0ng Anh Gia Lai"
    },
    {
        "id": "TIER_CUP-2013-1/8-DAN-BIDU",
        "competitionId": "National Cup",
        "competitionTier": "TIER_CUP",
        "season": "2013",
        "round": "1/8",
        "status": "FINISHED",
        "date": "2013-03-25",
        "time": "16:30",
        "stadium": "H\u00f2a Xu\u00e2n",
        "homeId": "DAN",
        "homeTeam": "SHB \u0110\u00e0 N\u1eb5ng",
        "homeScore": "3",
        "awayScore": "2",
        "awayId": "BIDU",
        "awayTeam": "Becamex B\u00ecnh D\u01b0\u01a1ng",
        "note": "SHB \u0110\u00e0 N\u1eb5ng"
    },
    {
        "id": "TIER_CUP-2013-1/8-DON-BIDI",
        "competitionId": "National Cup",
        "competitionTier": "TIER_CUP",
        "season": "2013",
        "round": "1/8",
        "status": "FINISHED",
        "date": "2013-03-26",
        "time": "15:30",
        "stadium": "\u0110\u1ed3ng Nai",
        "homeId": "DON",
        "homeTeam": "\u0110\u1ed3ng Nai",
        "homeScore": "3",
        "awayScore": "1",
        "awayId": "BIDI",
        "awayTeam": "Topenland B\u00ecnh \u0110\u1ecbnh",
        "note": "\u0110\u1ed3ng Nai"
    },
    {
        "id": "TIER_CUP-2013-1/8-ANGI-LAN",
        "competitionId": "National Cup",
        "competitionTier": "TIER_CUP",
        "season": "2013",
        "round": "1/8",
        "status": "FINISHED",
        "date": "2013-03-26",
        "time": "15:30",
        "stadium": "Ki\u00ean Giang",
        "homeId": "ANGI",
        "homeTeam": "An Giang",
        "homeScore": "1",
        "awayScore": "5",
        "awayId": "LAN",
        "awayTeam": "Long An",
        "note": "Long An"
    },
    {
        "id": "TIER_CUP-2013-1/8-THH-NAN",
        "competitionId": "National Cup",
        "competitionTier": "TIER_CUP",
        "season": "2013",
        "round": "1/8",
        "status": "FINISHED",
        "date": "2013-03-26",
        "time": "16:00",
        "stadium": "Thanh H\u00f3a",
        "homeId": "THH",
        "homeTeam": "\u0110\u00f4ng \u00c1 Thanh H\u00f3a",
        "homeScore": "0",
        "awayScore": "0",
        "awayId": "NAN",
        "awayTeam": "S\u00f4ng Lam Ngh\u1ec7 An",
        "note": "\u0110\u00f4ng \u00c1 Thanh H\u00f3a"
    },
    {
        "id": "TIER_CUP-2013-1/8-NIB-QNI",
        "competitionId": "National Cup",
        "competitionTier": "TIER_CUP",
        "season": "2013",
        "round": "1/8",
        "status": "FINISHED",
        "date": "2013-03-26",
        "time": "16:00",
        "stadium": "Ninh B\u00ecnh",
        "homeId": "NIB",
        "homeTeam": "XM The Vissai Ninh B\u00ecnh",
        "homeScore": "2",
        "awayScore": "1",
        "awayId": "QNI",
        "awayTeam": "Than Qu\u1ea3ng Ninh",
        "note": "XM The Vissai Ninh B\u00ecnh"
    },
    {
        "id": "TIER_CUP-2013-quarterfinal-THH-DON",
        "competitionId": "National Cup",
        "competitionTier": "TIER_CUP",
        "season": "2013",
        "round": "quarterfinal",
        "status": "FINISHED",
        "date": "2013-07-10",
        "time": "17:00",
        "stadium": "Thanh H\u00f3a",
        "homeId": "THH",
        "homeTeam": "\u0110\u00f4ng \u00c1 Thanh H\u00f3a",
        "homeScore": "0",
        "awayScore": "1",
        "awayId": "DON",
        "awayTeam": "\u0110\u1ed3ng Nai",
        "note": "\u0110\u1ed3ng Nai"
    },
    {
        "id": "TIER_CUP-2013-quarterfinal-NIB-GLA",
        "competitionId": "National Cup",
        "competitionTier": "TIER_CUP",
        "season": "2013",
        "round": "quarterfinal",
        "status": "FINISHED",
        "date": "2013-07-10",
        "time": "17:00",
        "stadium": "Ninh B\u00ecnh",
        "homeId": "NIB",
        "homeTeam": "XM The Vissai Ninh B\u00ecnh",
        "homeScore": "2",
        "awayScore": "1",
        "awayId": "GLA",
        "awayTeam": "Ho\u00e0ng Anh Gia Lai",
        "note": "XM The Vissai Ninh B\u00ecnh"
    },
    {
        "id": "TIER_CUP-2013-quarterfinal-DAN-QNA",
        "competitionId": "National Cup",
        "competitionTier": "TIER_CUP",
        "season": "2013",
        "round": "quarterfinal",
        "status": "FINISHED",
        "date": "2013-07-11",
        "time": "16:30",
        "stadium": "H\u00f2a Xu\u00e2n",
        "homeId": "DAN",
        "homeTeam": "SHB \u0110\u00e0 N\u1eb5ng",
        "homeScore": "3",
        "awayScore": "0",
        "awayId": "QNA",
        "awayTeam": "Qu\u1ea3ng Nam",
        "note": "SHB \u0110\u00e0 N\u1eb5ng"
    },
    {
        "id": "TIER_CUP-2013-quarterfinal-LAN-HAN",
        "competitionId": "National Cup",
        "competitionTier": "TIER_CUP",
        "season": "2013",
        "round": "quarterfinal",
        "status": "FINISHED",
        "date": "2013-07-11",
        "time": "17:00",
        "stadium": "Long An",
        "homeId": "LAN",
        "homeTeam": "Long An",
        "homeScore": "2",
        "awayScore": "1",
        "awayId": "HAN",
        "awayTeam": "H\u00e0 N\u1ed9i",
        "note": "Long An"
    },
    {
        "id": "TIER_CUP-2013-semifinal-DON-DAN",
        "competitionId": "National Cup",
        "competitionTier": "TIER_CUP",
        "season": "2013",
        "round": "semifinal",
        "status": "FINISHED",
        "date": "2013-08-07",
        "time": "16:00",
        "stadium": "\u0110\u1ed3ng Nai",
        "homeId": "DON",
        "homeTeam": "\u0110\u1ed3ng Nai",
        "homeScore": "4",
        "awayScore": "4",
        "awayId": "DAN",
        "awayTeam": "SHB \u0110\u00e0 N\u1eb5ng",
        "note": "SHB \u0110\u00e0 N\u1eb5ng"
    },
    {
        "id": "TIER_CUP-2013-semifinal-LAN-NIB",
        "competitionId": "National Cup",
        "competitionTier": "TIER_CUP",
        "season": "2013",
        "round": "semifinal",
        "status": "FINISHED",
        "date": "2013-08-07",
        "time": "17:00",
        "stadium": "Long An",
        "homeId": "LAN",
        "homeTeam": "Long An",
        "homeScore": "3",
        "awayScore": "3",
        "awayId": "NIB",
        "awayTeam": "XM The Vissai Ninh B\u00ecnh",
        "note": "XM The Vissai Ninh B\u00ecnh"
    },
    {
        "id": "TIER_CUP-2013-final-DAN-NIB",
        "competitionId": "National Cup",
        "competitionTier": "TIER_CUP",
        "season": "2013",
        "round": "final",
        "status": "FINISHED",
        "date": "2013-09-05",
        "time": "16:00",
        "stadium": "H\u00f2a Xu\u00e2n",
        "homeId": "DAN",
        "homeTeam": "SHB \u0110\u00e0 N\u1eb5ng",
        "homeScore": "1",
        "awayScore": "1",
        "awayId": "NIB",
        "awayTeam": "XM The Vissai Ninh B\u00ecnh",
        "note": "XM The Vissai Ninh B\u00ecnh"
    }
]