[
  {
    "symbol": "AAM",
    "market": "HOSE",
    "name": "Mekong Fisheries Joint Stock Company",
    "industry": "Consumer Goods",
    "supersector": "Food & Beverage",
    "sector": "Food Producers",
    "subsector": "Farming & Fishing",
    "listedDate": "2009-09-24",
    "issueShare": "12346411",
    "marketCap": "128026979500",
    "priceChangedFiveDayPercent": "N/A",
    "priceChangedOneMonthPercent": "N/A",
    "priceChangedThreeMonthsPercent": "N/A"
  },
  {
    "symbol": "ABT",
    "market": "HOSE",
    "name": "Bentre Aquaproduct Import And Export Joint Stock Company",
    "industry": "Consumer Goods",
    "supersector": "Food & Beverage",
    "sector": "Food Producers",
    "subsector": "Farming & Fishing",
    "listedDate": "2006-12-25",
    "issueShare": "14387207",
    "marketCap": "442824863200",
    "priceChangedFiveDayPercent": "N/A",
    "priceChangedOneMonthPercent": "N/A",
    "priceChangedThreeMonthsPercent": "N/A"
  },
  {
    "symbol": "ACL",
    "market": "HOSE",
    "name": "Cuu Long An Giang Fish Joint Stock Company",
    "industry": "Consumer Goods",
    "supersector": "Food & Beverage",
    "sector": "Food Producers",
    "subsector": "Farming & Fishing",
    "listedDate": "2007-09-05",
    "issueShare": "50159019",
    "marketCap": "945497508150",
    "priceChangedFiveDayPercent": "N/A",
    "priceChangedOneMonthPercent": "N/A",
    "priceChangedThreeMonthsPercent": "N/A"
  },
  {
    "symbol": "AGF",
    "market": "UPCOM",
    "name": "An Giang Fisheries Import and Export Joint Stock Company",
    "industry": "Consumer Goods",
    "supersector": "Food & Beverage",
    "sector": "Food Producers",
    "subsector": "Farming & Fishing",
    "listedDate": "2002-05-02",
    "issueShare": "28109743",
    "marketCap": "74715696894",
    "priceChangedFiveDayPercent": "N/A",
    "priceChangedOneMonthPercent": "N/A",
    "priceChangedThreeMonthsPercent": "N/A"
  },
  {
    "symbol": "ANV",
    "market": "HOSE",
    "name": "Nam Viet Corporation",
    "industry": "Consumer Goods",
    "supersector": "Food & Beverage",
    "sector": "Food Producers",
    "subsector": "Farming & Fishing",
    "listedDate": "2007-12-07",
    "issueShare": "127539625",
    "marketCap": "6191127512500",
    "priceChangedFiveDayPercent": "N/A",
    "priceChangedOneMonthPercent": "N/A",
    "priceChangedThreeMonthsPercent": "N/A"
  },
  {
    "symbol": "APT",
    "market": "UPCOM",
    "name": "Saigon Aquatic Product Trading Joint Stock Company",
    "industry": "Consumer Goods",
    "supersector": "Food & Beverage",
    "sector": "Food Producers",
    "subsector": "Farming & Fishing",
    "listedDate": "2019-06-07",
    "issueShare": "8800000",
    "marketCap": "23760000000",
    "priceChangedFiveDayPercent": "N/A",
    "priceChangedOneMonthPercent": "N/A",
    "priceChangedThreeMonthsPercent": "N/A"
  },
  {
    "symbol": "ASM",
    "market": "HOSE",
    "name": "Sao Mai Group Corporation",
    "industry": "Consumer Goods",
    "supersector": "Food & Beverage",
    "sector": "Food Producers",
    "subsector": "Farming & Fishing",
    "listedDate": "2010-01-18",
    "issueShare": "336526752",
    "marketCap": "5687302108800",
    "priceChangedFiveDayPercent": "N/A",
    "priceChangedOneMonthPercent": "N/A",
    "priceChangedThreeMonthsPercent": "N/A"
  },
  {
    "symbol": "ATA",
    "market": "UPCOM",
    "name": "NTACO Corporation",
    "industry": "Consumer Goods",
    "supersector": "Food & Beverage",
    "sector": "Food Producers",
    "subsector": "Farming & Fishing",
    "listedDate": "2009-09-08",
    "issueShare": "11999998",
    "marketCap": "25379995770",
    "priceChangedFiveDayPercent": "N/A",
    "priceChangedOneMonthPercent": "N/A",
    "priceChangedThreeMonthsPercent": "N/A"
  },
  {
    "symbol": "AUM",
    "market": "UPCOM",
    "name": "Vinacafe Son Thanh Joint Stock Company",
    "industry": "Consumer Goods",
    "supersector": "Food & Beverage",
    "sector": "Food Producers",
    "subsector": "Farming & Fishing",
    "listedDate": "2016-09-26",
    "issueShare": "1000000",
    "marketCap": "10500000000",
    "priceChangedFiveDayPercent": "N/A",
    "priceChangedOneMonthPercent": "N/A",
    "priceChangedThreeMonthsPercent": "N/A"
  },
  {
    "symbol": "AVF",
    "market": "UPCOM",
    "name": "Anvifish Joint Stock Company",
    "industry": "Consumer Goods",
    "supersector": "Food & Beverage",
    "sector": "Food Producers",
    "subsector": "Farming & Fishing",
    "listedDate": "2010-11-23",
    "issueShare": "43338000",
    "marketCap": "39047538000",
    "priceChangedFiveDayPercent": "N/A",
    "priceChangedOneMonthPercent": "N/A",
    "priceChangedThreeMonthsPercent": "N/A"
  },
  {
    "symbol": "BAF",
    "market": "HOSE",
    "name": "BAF Vietnam Agriculture Joint Stock Company",
    "industry": "Consumer Goods",
    "supersector": "Food & Beverage",
    "sector": "Food Producers",
    "subsector": "Farming & Fishing",
    "listedDate": "2021-12-03",
    "issueShare": "143520000",
    "marketCap": "3867864000000",
    "priceChangedFiveDayPercent": "N/A",
    "priceChangedOneMonthPercent": "N/A",
    "priceChangedThreeMonthsPercent": "N/A"
  },
  {
    "symbol": "BLF",
    "market": "HNX",
    "name": "Bac Lieu Fisheries Joint Stock Company",
    "industry": "Consumer Goods",
    "supersector": "Food & Beverage",
    "sector": "Food Producers",
    "subsector": "Farming & Fishing",
    "listedDate": "2008-06-02",
    "issueShare": "11500000",
    "marketCap": "36799996800",
    "priceChangedFiveDayPercent": "N/A",
    "priceChangedOneMonthPercent": "N/A",
    "priceChangedThreeMonthsPercent": "N/A"
  },
  {
    "symbol": "CAD",
    "market": "UPCOM",
    "name": "Cadovimex Seafood Import-Export And Processing Joint Stock Company",
    "industry": "Consumer Goods",
    "supersector": "Food & Beverage",
    "sector": "Food Producers",
    "subsector": "Farming & Fishing",
    "listedDate": "2012-11-01",
    "issueShare": "8799927",
    "marketCap": "37439868600",
    "priceChangedFiveDayPercent": "N/A",
    "priceChangedOneMonthPercent": "N/A",
    "priceChangedThreeMonthsPercent": "N/A"
  },
  {
    "symbol": "CAT",
    "market": "UPCOM",
    "name": "Ca Mau Joint Stock Seafoods Company",
    "industry": "Consumer Goods",
    "supersector": "Food & Beverage",
    "sector": "Food Producers",
    "subsector": "Farming & Fishing",
    "listedDate": "2018-03-23",
    "issueShare": "9748579",
    "marketCap": "205778857500",
    "priceChangedFiveDayPercent": "N/A",
    "priceChangedOneMonthPercent": "N/A",
    "priceChangedThreeMonthsPercent": "N/A"
  },
  {
    "symbol": "CCA",
    "market": "UPCOM",
    "name": "Can Tho Import Export Seafood Joint Stock Company",
    "industry": "Consumer Goods",
    "supersector": "Food & Beverage",
    "sector": "Food Producers",
    "subsector": "Farming & Fishing",
    "listedDate": "2019-12-26",
    "issueShare": "15092326",
    "marketCap": "236705782995",
    "priceChangedFiveDayPercent": "N/A",
    "priceChangedOneMonthPercent": "N/A",
    "priceChangedThreeMonthsPercent": "N/A"
  },
  {
    "symbol": "CMX",
    "market": "HOSE",
    "name": "CAMIMEX Group Joint Stock Company",
    "industry": "Consumer Goods",
    "supersector": "Food & Beverage",
    "sector": "Food Producers",
    "subsector": "Farming & Fishing",
    "listedDate": "2010-11-09",
    "issueShare": "101898990",
    "marketCap": "1416395961000",
    "priceChangedFiveDayPercent": "N/A",
    "priceChangedOneMonthPercent": "N/A",
    "priceChangedThreeMonthsPercent": "N/A"
  },
  {
    "symbol": "CNA",
    "market": "UPCOM",
    "name": "Nghe An Tea Corporation Joint Stock Company",
    "industry": "Consumer Goods",
    "supersector": "Food & Beverage",
    "sector": "Food Producers",
    "subsector": "Farming & Fishing",
    "listedDate": "2021-12-09",
    "issueShare": "793917",
    "marketCap": "149942864500",
    "priceChangedFiveDayPercent": "N/A",
    "priceChangedOneMonthPercent": "N/A",
    "priceChangedThreeMonthsPercent": "N/A"
  },
  {
    "symbol": "CQN",
    "market": "UPCOM",
    "name": "Quang Ninh Port Joint Stock Company",
    "industry": "Consumer Goods",
    "supersector": "Food & Beverage",
    "sector": "Food Producers",
    "subsector": "Farming & Fishing",
    "listedDate": "2020-08-18",
    "issueShare": "75049936",
    "marketCap": "1531018694400",
    "priceChangedFiveDayPercent": "N/A",
    "priceChangedOneMonthPercent": "N/A",
    "priceChangedThreeMonthsPercent": "N/A"
  },
  {
    "symbol": "DAT",
    "market": "HOSE",
    "name": "Travel Investment and Seafood Development Corporation",
    "industry": "Consumer Goods",
    "supersector": "Food & Beverage",
    "sector": "Food Producers",
    "subsector": "Farming & Fishing",
    "listedDate": "2015-11-05",
    "issueShare": "62935104",
    "marketCap": "1047869481600",
    "priceChangedFiveDayPercent": "N/A",
    "priceChangedOneMonthPercent": "N/A",
    "priceChangedThreeMonthsPercent": "N/A"
  },
  {
    "symbol": "DBC",
    "market": "HOSE",
    "name": "DABACO Group",
    "industry": "Consumer Goods",
    "supersector": "Food & Beverage",
    "sector": "Food Producers",
    "subsector": "Farming & Fishing",
    "listedDate": "2008-03-18",
    "issueShare": "242001859",
    "marketCap": "6364648891700",
    "priceChangedFiveDayPercent": "N/A",
    "priceChangedOneMonthPercent": "N/A",
    "priceChangedThreeMonthsPercent": "N/A"
  },
  {
    "symbol": "DMN",
    "market": "UPCOM",
    "name": "Domenal Joint Stock Company",
    "industry": "Consumer Goods",
    "supersector": "Food & Beverage",
    "sector": "Food Producers",
    "subsector": "Farming & Fishing",
    "listedDate": "2021-11-22",
    "issueShare": "12500000",
    "marketCap": "98912500000",
    "priceChangedFiveDayPercent": "N/A",
    "priceChangedOneMonthPercent": "N/A",
    "priceChangedThreeMonthsPercent": "N/A"
  },
  {
    "symbol": "FMC",
    "market": "HOSE",
    "name": "Sao Ta Foods Joint Stock Company",
    "industry": "Consumer Goods",
    "supersector": "Food & Beverage",
    "sector": "Food Producers",
    "subsector": "Farming & Fishing",
    "listedDate": "2006-12-07",
    "issueShare": "65388889",
    "marketCap": "3302138894500",
    "priceChangedFiveDayPercent": "N/A",
    "priceChangedOneMonthPercent": "N/A",
    "priceChangedThreeMonthsPercent": "N/A"
  },
  {
    "symbol": "HAG",
    "market": "HOSE",
    "name": "Hoang Anh Gia Lai Corporation",
    "industry": "Consumer Goods",
    "supersector": "Food & Beverage",
    "sector": "Food Producers",
    "subsector": "Farming & Fishing",
    "listedDate": "2008-12-22",
    "issueShare": "927467947",
    "marketCap": "12612630248800",
    "priceChangedFiveDayPercent": "N/A",
    "priceChangedOneMonthPercent": "N/A",
    "priceChangedThreeMonthsPercent": "N/A"
  },
  {
    "symbol": "HNG",
    "market": "HOSE",
    "name": "Hoang Anh Gia Lai Agricultural Joint Stock Company",
    "industry": "Consumer Goods",
    "supersector": "Food & Beverage",
    "sector": "Food Producers",
    "subsector": "Farming & Fishing",
    "listedDate": "2015-07-20",
    "issueShare": "1108553895",
    "marketCap": "6773264298450",
    "priceChangedFiveDayPercent": "N/A",
    "priceChangedOneMonthPercent": "N/A",
    "priceChangedThreeMonthsPercent": "N/A"
  },
  {
    "symbol": "HVA",
    "market": "UPCOM",
    "name": "HVA Investment Joint Stock Company",
    "industry": "Consumer Goods",
    "supersector": "Food & Beverage",
    "sector": "Food Producers",
    "subsector": "Farming & Fishing",
    "listedDate": "2015-07-30",
    "issueShare": "13650000",
    "marketCap": "81913650000",
    "priceChangedFiveDayPercent": "N/A",
    "priceChangedOneMonthPercent": "N/A",
    "priceChangedThreeMonthsPercent": "N/A"
  },
  {
    "symbol": "HVG",
    "market": "UPCOM",
    "name": "Hung Vuong Corporation",
    "industry": "Consumer Goods",
    "supersector": "Food & Beverage",
    "sector": "Food Producers",
    "subsector": "Farming & Fishing",
    "listedDate": "2009-11-25",
    "issueShare": "227038291",
    "marketCap": "644788746440",
    "priceChangedFiveDayPercent": "N/A",
    "priceChangedOneMonthPercent": "N/A",
    "priceChangedThreeMonthsPercent": "N/A"
  },
  {
    "symbol": "ICF",
    "market": "UPCOM",
    "name": "Incomfish Corp",
    "industry": "Consumer Goods",
    "supersector": "Food & Beverage",
    "sector": "Food Producers",
    "subsector": "Farming & Fishing",
    "listedDate": "2007-12-18",
    "issueShare": "12807000",
    "marketCap": "36218196000",
    "priceChangedFiveDayPercent": "N/A",
    "priceChangedOneMonthPercent": "N/A",
    "priceChangedThreeMonthsPercent": "N/A"
  },
  {
    "symbol": "IDI",
    "market": "HOSE",
    "name": "I.D.I International Development & Investment Corporation",
    "industry": "Consumer Goods",
    "supersector": "Food & Beverage",
    "sector": "Food Producers",
    "subsector": "Farming & Fishing",
    "listedDate": "2011-06-30",
    "issueShare": "227644608",
    "marketCap": "4860212380800",
    "priceChangedFiveDayPercent": "N/A",
    "priceChangedOneMonthPercent": "N/A",
    "priceChangedThreeMonthsPercent": "N/A"
  },
  {
    "symbol": "ILA",
    "market": "UPCOM",
    "name": "ILA Joint Stock Company",
    "industry": "Consumer Goods",
    "supersector": "Food & Beverage",
    "sector": "Food Producers",
    "subsector": "Farming & Fishing",
    "listedDate": "2017-11-28",
    "issueShare": "18529939",
    "marketCap": "107640415651",
    "priceChangedFiveDayPercent": "N/A",
    "priceChangedOneMonthPercent": "N/A",
    "priceChangedThreeMonthsPercent": "N/A"
  },
  {
    "symbol": "JOS",
    "market": "UPCOM",
    "name": "Minh Hai Export Frozen Seafood Processing Joint Stock Company",
    "industry": "Consumer Goods",
    "supersector": "Food & Beverage",
    "sector": "Food Producers",
    "subsector": "Farming & Fishing",
    "listedDate": "2017-07-28",
    "issueShare": "15322723",
    "marketCap": "18172138488",
    "priceChangedFiveDayPercent": "N/A",
    "priceChangedOneMonthPercent": "N/A",
    "priceChangedThreeMonthsPercent": "N/A"
  },
  {
    "symbol": "KHS",
    "market": "HNX",
    "name": "Kien Hung Joint Stock Company",
    "industry": "Consumer Goods",
    "supersector": "Food & Beverage",
    "sector": "Food Producers",
    "subsector": "Farming & Fishing",
    "listedDate": "2017-12-26",
    "issueShare": "12090969",
    "marketCap": "193455504000",
    "priceChangedFiveDayPercent": "N/A",
    "priceChangedOneMonthPercent": "N/A",
    "priceChangedThreeMonthsPercent": "N/A"
  },
  {
    "symbol": "MLS",
    "market": "UPCOM",
    "name": "Mitraco Livestock Joint Stock Company",
    "industry": "Consumer Goods",
    "supersector": "Food & Beverage",
    "sector": "Food Producers",
    "subsector": "Farming & Fishing",
    "listedDate": "2016-12-28",
    "issueShare": "4000000",
    "marketCap": "78636000000",
    "priceChangedFiveDayPercent": "N/A",
    "priceChangedOneMonthPercent": "N/A",
    "priceChangedThreeMonthsPercent": "N/A"
  },
  {
    "symbol": "MPC",
    "market": "UPCOM",
    "name": "Minh Phu Seafood Corporation",
    "industry": "Consumer Goods",
    "supersector": "Food & Beverage",
    "sector": "Food Producers",
    "subsector": "Farming & Fishing",
    "listedDate": "2017-10-16",
    "issueShare": "200000000",
    "marketCap": "9188810323050",
    "priceChangedFiveDayPercent": "N/A",
    "priceChangedOneMonthPercent": "N/A",
    "priceChangedThreeMonthsPercent": "N/A"
  },
  {
    "symbol": "NGC",
    "market": "UPCOM",
    "name": "Ngo Quyen Processing Export Joint Stock Company",
    "industry": "Consumer Goods",
    "supersector": "Food & Beverage",
    "sector": "Food Producers",
    "subsector": "Farming & Fishing",
    "listedDate": "2008-03-06",
    "issueShare": "2299854",
    "marketCap": "44847153000",
    "priceChangedFiveDayPercent": "N/A",
    "priceChangedOneMonthPercent": "N/A",
    "priceChangedThreeMonthsPercent": "N/A"
  },
  {
    "symbol": "NSC",
    "market": "HOSE",
    "name": "Vietnam National Seed Group Joint Stock Company",
    "industry": "Consumer Goods",
    "supersector": "Food & Beverage",
    "sector": "Food Producers",
    "subsector": "Farming & Fishing",
    "listedDate": "2006-12-21",
    "issueShare": "17586988",
    "marketCap": "1456927376400",
    "priceChangedFiveDayPercent": "N/A",
    "priceChangedOneMonthPercent": "N/A",
    "priceChangedThreeMonthsPercent": "N/A"
  },
  {
    "symbol": "NSS",
    "market": "UPCOM",
    "name": "Dong Nai Agricultural Livestock Product Joint Stock Company",
    "industry": "Consumer Goods",
    "supersector": "Food & Beverage",
    "sector": "Food Producers",
    "subsector": "Farming & Fishing",
    "listedDate": "2018-10-30",
    "issueShare": "10263942",
    "marketCap": "41055768000",
    "priceChangedFiveDayPercent": "N/A",
    "priceChangedOneMonthPercent": "N/A",
    "priceChangedThreeMonthsPercent": "N/A"
  },
  {
    "symbol": "PRT",
    "market": "UPCOM",
    "name": "Binh Duong Producing and Trading Corporation",
    "industry": "Consumer Goods",
    "supersector": "Food & Beverage",
    "sector": "Food Producers",
    "subsector": "Farming & Fishing",
    "listedDate": "2018-05-07",
    "issueShare": "300000000",
    "marketCap": "4221600000000",
    "priceChangedFiveDayPercent": "N/A",
    "priceChangedOneMonthPercent": "N/A",
    "priceChangedThreeMonthsPercent": "N/A"
  },
  {
    "symbol": "PSL",
    "market": "UPCOM",
    "name": "Phu Son LiveStock Joint Stock Company",
    "industry": "Consumer Goods",
    "supersector": "Food & Beverage",
    "sector": "Food Producers",
    "subsector": "Farming & Fishing",
    "listedDate": "2010-05-17",
    "issueShare": "11812500",
    "marketCap": "212625000000",
    "priceChangedFiveDayPercent": "N/A",
    "priceChangedOneMonthPercent": "N/A",
    "priceChangedThreeMonthsPercent": "N/A"
  },
  {
    "symbol": "SCV",
    "market": "UPCOM",
    "name": "Vietnam National Salt Joint Stock Company",
    "industry": "Consumer Goods",
    "supersector": "Food & Beverage",
    "sector": "Food Producers",
    "subsector": "Farming & Fishing",
    "listedDate": "2021-05-19",
    "issueShare": "1279392",
    "marketCap": "102674320000",
    "priceChangedFiveDayPercent": "N/A",
    "priceChangedOneMonthPercent": "N/A",
    "priceChangedThreeMonthsPercent": "N/A"
  },
  {
    "symbol": "SEA",
    "market": "UPCOM",
    "name": "Viet Nam Seaproducts Joint Stock Corporation",
    "industry": "Consumer Goods",
    "supersector": "Food & Beverage",
    "sector": "Food Producers",
    "subsector": "Farming & Fishing",
    "listedDate": "2016-12-23",
    "issueShare": "125000000",
    "marketCap": "3234754140000",
    "priceChangedFiveDayPercent": "N/A",
    "priceChangedOneMonthPercent": "N/A",
    "priceChangedThreeMonthsPercent": "N/A"
  },
  {
    "symbol": "SJ1",
    "market": "HNX",
    "name": "Hung Hau Agricultural Corporation",
    "industry": "Consumer Goods",
    "supersector": "Food & Beverage",
    "sector": "Food Producers",
    "subsector": "Farming & Fishing",
    "listedDate": "2006-12-29",
    "issueShare": "23485154",
    "marketCap": "321732772800",
    "priceChangedFiveDayPercent": "N/A",
    "priceChangedOneMonthPercent": "N/A",
    "priceChangedThreeMonthsPercent": "N/A"
  },
  {
    "symbol": "SNC",
    "market": "UPCOM",
    "name": "Nam Can Seaproducts Import Export Joint Stock Company",
    "industry": "Consumer Goods",
    "supersector": "Food & Beverage",
    "sector": "Food Producers",
    "subsector": "Farming & Fishing",
    "listedDate": "2014-11-11",
    "issueShare": "5000000",
    "marketCap": "75500000000",
    "priceChangedFiveDayPercent": "N/A",
    "priceChangedOneMonthPercent": "N/A",
    "priceChangedThreeMonthsPercent": "N/A"
  },
  {
    "symbol": "SPD",
    "market": "UPCOM",
    "name": "Danang Seaproducts Import - Export Corporation",
    "industry": "Consumer Goods",
    "supersector": "Food & Beverage",
    "sector": "Food Producers",
    "subsector": "Farming & Fishing",
    "listedDate": "2010-04-22",
    "issueShare": "12000000",
    "marketCap": "120000000000",
    "priceChangedFiveDayPercent": "N/A",
    "priceChangedOneMonthPercent": "N/A",
    "priceChangedThreeMonthsPercent": "N/A"
  },
  {
    "symbol": "SPH",
    "market": "UPCOM",
    "name": "Ha Noi Seaproducts Import Export Joint Stock Corporation",
    "industry": "Consumer Goods",
    "supersector": "Food & Beverage",
    "sector": "Food Producers",
    "subsector": "Farming & Fishing",
    "listedDate": "2014-05-20",
    "issueShare": "10000000",
    "marketCap": "220000000000",
    "priceChangedFiveDayPercent": "N/A",
    "priceChangedOneMonthPercent": "N/A",
    "priceChangedThreeMonthsPercent": "N/A"
  },
  {
    "symbol": "SPV",
    "market": "UPCOM",
    "name": "Special Aquatic Products Joint Stock Company",
    "industry": "Consumer Goods",
    "supersector": "Food & Beverage",
    "sector": "Food Producers",
    "subsector": "Farming & Fishing",
    "listedDate": "2017-02-14",
    "issueShare": "10800000",
    "marketCap": "184680000000",
    "priceChangedFiveDayPercent": "N/A",
    "priceChangedOneMonthPercent": "N/A",
    "priceChangedThreeMonthsPercent": "N/A"
  },
  {
    "symbol": "SSC",
    "market": "HOSE",
    "name": "Southern Seed Joint-stock Company",
    "industry": "Consumer Goods",
    "supersector": "Food & Beverage",
    "sector": "Food Producers",
    "subsector": "Farming & Fishing",
    "listedDate": "2005-03-01",
    "issueShare": "14992367",
    "marketCap": "504327830000",
    "priceChangedFiveDayPercent": "N/A",
    "priceChangedOneMonthPercent": "N/A",
    "priceChangedThreeMonthsPercent": "N/A"
  },
  {
    "symbol": "SSN",
    "market": "UPCOM",
    "name": "Saigon Sea Products Import Export Joint Stock Corporation",
    "industry": "Consumer Goods",
    "supersector": "Food & Beverage",
    "sector": "Food Producers",
    "subsector": "Farming & Fishing",
    "listedDate": "2013-10-15",
    "issueShare": "39600000",
    "marketCap": "264290400000",
    "priceChangedFiveDayPercent": "N/A",
    "priceChangedOneMonthPercent": "N/A",
    "priceChangedThreeMonthsPercent": "N/A"
  },
  {
    "symbol": "TAR",
    "market": "HNX",
    "name": "Trung An Hi-tech Farming Joint Stock Company",
    "industry": "Consumer Goods",
    "supersector": "Food & Beverage",
    "sector": "Food Producers",
    "subsector": "Farming & Fishing",
    "listedDate": "2019-02-20",
    "issueShare": "71199933",
    "marketCap": "1901038211100",
    "priceChangedFiveDayPercent": "N/A",
    "priceChangedOneMonthPercent": "N/A",
    "priceChangedThreeMonthsPercent": "N/A"
  },
  {
    "symbol": "TCJ",
    "market": "UPCOM",
    "name": "To Chau Joint Stock Company",
    "industry": "Consumer Goods",
    "supersector": "Food & Beverage",
    "sector": "Food Producers",
    "subsector": "Farming & Fishing",
    "listedDate": "2017-11-24",
    "issueShare": "10000000",
    "marketCap": "51000000000",
    "priceChangedFiveDayPercent": "N/A",
    "priceChangedOneMonthPercent": "N/A",
    "priceChangedThreeMonthsPercent": "N/A"
  },
  {
    "symbol": "THP",
    "market": "UPCOM",
    "name": "Thuan Phuoc Seafoods and trading corporation",
    "industry": "Consumer Goods",
    "supersector": "Food & Beverage",
    "sector": "Food Producers",
    "subsector": "Farming & Fishing",
    "listedDate": "2019-11-18",
    "issueShare": "21611185",
    "marketCap": "216107850000",
    "priceChangedFiveDayPercent": "N/A",
    "priceChangedOneMonthPercent": "N/A",
    "priceChangedThreeMonthsPercent": "N/A"
  },
  {
    "symbol": "TS4",
    "market": "UPCOM",
    "name": "Seafood Joint Stock Company No 4",
    "industry": "Consumer Goods",
    "supersector": "Food & Beverage",
    "sector": "Food Producers",
    "subsector": "Farming & Fishing",
    "listedDate": "2002-08-08",
    "issueShare": "16160646",
    "marketCap": "40754997166",
    "priceChangedFiveDayPercent": "N/A",
    "priceChangedOneMonthPercent": "N/A",
    "priceChangedThreeMonthsPercent": "N/A"
  },
  {
    "symbol": "VHC",
    "market": "HOSE",
    "name": "Vinh Hoan Corporation",
    "industry": "Consumer Goods",
    "supersector": "Food & Beverage",
    "sector": "Food Producers",
    "subsector": "Farming & Fishing",
    "listedDate": "2007-12-24",
    "issueShare": "183376956",
    "marketCap": "16503926040000",
    "priceChangedFiveDayPercent": "N/A",
    "priceChangedOneMonthPercent": "N/A",
    "priceChangedThreeMonthsPercent": "N/A"
  },
  {
    "symbol": "VLC",
    "market": "UPCOM",
    "name": "Vietnam LiveStock Corporation",
    "industry": "Consumer Goods",
    "supersector": "Food & Beverage",
    "sector": "Food Producers",
    "subsector": "Farming & Fishing",
    "listedDate": "2015-10-26",
    "issueShare": "172346173",
    "marketCap": "3807471653916",
    "priceChangedFiveDayPercent": "N/A",
    "priceChangedOneMonthPercent": "N/A",
    "priceChangedThreeMonthsPercent": "N/A"
  },
  {
    "symbol": "VNH",
    "market": "UPCOM",
    "name": "Viet Viet Nhat Investment Corporation",
    "industry": "Consumer Goods",
    "supersector": "Food & Beverage",
    "sector": "Food Producers",
    "subsector": "Farming & Fishing",
    "listedDate": "2010-04-08",
    "issueShare": "8023071",
    "marketCap": "25505342709",
    "priceChangedFiveDayPercent": "N/A",
    "priceChangedOneMonthPercent": "N/A",
    "priceChangedThreeMonthsPercent": "N/A"
  }
]
