[
    {
        "name": "Thai Nguyen International Hospital Joint Stock Company",
        "market_cap": "1543281190500.0",
        "sector": "Health Care Equipment & Services",
        "symbol": "TNH",
        "supersector": "Health Care",
        "industry": "Health Care",
        "listing_date": "06/01/2021 00:00:00",
        "subsector": "Health Care Providers",
        "issue_share": "51874998.0",
        "listed_value": "51874998.0"
    },
    {
        "name": "Tam Duc Cardiology Hospital Joint Stock Company",
        "market_cap": "780710400000.0",
        "sector": "Health Care Equipment & Services",
        "symbol": "TTD",
        "supersector": "Health Care",
        "industry": "Health Care",
        "listing_date": "06/02/2017 00:00:00",
        "subsector": "Health Care Providers",
        "issue_share": "15552000.0",
        "listed_value": "15552000.0"
    }
]