[
  {
    "symbol": "BTP",
    "market": "HOSE",
    "name": "Ba Ria Thermal Power Joint Stock Company",
    "industry": "Utilities",
    "supersector": "Utilities",
    "sector": "Electricity",
    "subsector": "Conventional Electricity",
    "listedDate": "2009-11-25",
    "issueShare": "60485600",
    "marketCap": "1070595120000",
    "priceChangedFiveDayPercent": "N/A",
    "priceChangedOneMonthPercent": "N/A",
    "priceChangedThreeMonthsPercent": "N/A"
  },
  {
    "symbol": "NBP",
    "market": "HNX",
    "name": "Ninh Binh Thermal Power Joint-Stock Company",
    "industry": "Utilities",
    "supersector": "Utilities",
    "sector": "Electricity",
    "subsector": "Conventional Electricity",
    "listedDate": "2009-08-06",
    "issueShare": "12865500",
    "marketCap": "212280750000",
    "priceChangedFiveDayPercent": "N/A",
    "priceChangedOneMonthPercent": "N/A",
    "priceChangedThreeMonthsPercent": "N/A"
  },
  {
    "symbol": "TBC",
    "market": "HOSE",
    "name": "Thac Ba Hydropower Joint Stock Company",
    "industry": "Utilities",
    "supersector": "Utilities",
    "sector": "Electricity",
    "subsector": "Conventional Electricity",
    "listedDate": "2009-10-19",
    "issueShare": "63500000",
    "marketCap": "1990725000000",
    "priceChangedFiveDayPercent": "N/A",
    "priceChangedOneMonthPercent": "N/A",
    "priceChangedThreeMonthsPercent": "N/A"
  },
  {
    "symbol": "VSH",
    "market": "HOSE",
    "name": "Vinh Son - Song Hinh Hydropower Joint Stock Company",
    "industry": "Utilities",
    "supersector": "Utilities",
    "sector": "Electricity",
    "subsector": "Conventional Electricity",
    "listedDate": "2006-07-18",
    "issueShare": "236241246",
    "marketCap": "10843473191400",
    "priceChangedFiveDayPercent": "N/A",
    "priceChangedOneMonthPercent": "N/A",
    "priceChangedThreeMonthsPercent": "N/A"
  }
]
